sphinx_tags/__init__.py
sphinx_tags-0.3.0.dist-info/LICENSE
sphinx_tags-0.3.0.dist-info/WHEEL
sphinx_tags-0.3.0.dist-info/METADATA
sphinx_tags-0.3.0.dist-info/RECORD
