Metadata-Version: 2.1
Name: sphinx-tags
Version: 0.3.0
Summary: Sphinx extension to create tags for documentation pages.
Keywords: documentation,sphinx
Author-email: melissawm <melissawm@gmail.com>
Classifier: License :: OSI Approved :: MIT License
Requires-Dist: sphinx>4
Requires-Dist: bs4 ; extra == "dev"
Requires-Dist: pytest>=6.0 ; extra == "dev"
Requires-Dist: pytest-cov ; extra == "dev"
Requires-Dist: pre-commit ; extra == "dev"
Requires-Dist: pydata-sphinx-theme ; extra == "sphinx"
Requires-Dist: sphinx-design ; extra == "sphinx"
Requires-Dist: nbsphinx ; extra == "sphinx"
Requires-Dist: myst-parser ; extra == "sphinx"
Project-URL: Home, https://github.com/melissawm/sphinx-tags
Provides-Extra: dev
Provides-Extra: sphinx
